compose_generator/__init__.py
compose_generator/example.env
compose_generator/example.py
compose_generator-0.2.0.dist-info/METADATA
compose_generator-0.2.0.dist-info/WHEEL
compose_generator-0.2.0.dist-info/RECORD
