Metadata-Version: 2.4
Name: compose-generator
Version: 0.2.0
Summary: Проект представляет собой генератор docker-compose.yml файла на основе настроек приложения
Author: pasha_danilevich
Author-email: danilevitch.pasha@yandex.ru
Requires-Python: >=3.10
Classifier: Programming Language :: Python :: 3
Classifier: Programming Language :: Python :: 3.10
Classifier: Programming Language :: Python :: 3.11
Classifier: Programming Language :: Python :: 3.12
Classifier: Programming Language :: Python :: 3.13
Classifier: Programming Language :: Python :: 3.14
Requires-Dist: pydantic-settings (>=2.11.0,<3.0.0)
